pfmath/__init__.py
pfmath-0.0.1.dev2.dist-info/LICENSE
pfmath-0.0.1.dev2.dist-info/METADATA
pfmath-0.0.1.dev2.dist-info/WHEEL
pfmath-0.0.1.dev2.dist-info/RECORD
